gild/__init__.py
gild/plugins/__init__.py
gild/plugins/errors/__init__.py
gild/plugins/errors/errors.py
gild/plugins/errors/manifest.enaml
gild/plugins/errors/plugin.py
gild/plugins/errors/widgets.enaml
gild/plugins/icons/__init__.py
gild/plugins/icons/icon_theme.py
gild/plugins/icons/manifest.enaml
gild/plugins/icons/plugin.py
gild/plugins/lifecycle/__init__.py
gild/plugins/lifecycle/app_window.enaml
gild/plugins/lifecycle/extensions.py
gild/plugins/lifecycle/manifest.enaml
gild/plugins/lifecycle/plugin.py
gild/plugins/log/__init__.py
gild/plugins/log/manifest.enaml
gild/plugins/log/plugin.py
gild/plugins/log/tools.py
gild/plugins/log/widgets.enaml
gild/plugins/packages/__init__.py
gild/plugins/packages/manifest.enaml
gild/plugins/packages/plugin.py
gild/plugins/preferences/__init__.py
gild/plugins/preferences/manifest.enaml
gild/plugins/preferences/plugin.py
gild/plugins/preferences/preferences.py
gild/plugins/states/__init__.py
gild/plugins/states/manifest.enaml
gild/plugins/states/plugin.py
gild/plugins/states/state.py
gild/testing/__init__.py
gild/testing/broken_enaml.enaml
gild/testing/fixtures.py
gild/testing/util.py
gild/testing/windows.enaml
gild/utils/__init__.py
gild/utils/argparse.py
gild/utils/atom_util.py
gild/utils/container_change.py
gild/utils/declarator.py
gild/utils/enaml_destroy_hook.py
gild/utils/mapping_utils.py
gild/utils/plugin_tools.py
gild/utils/priority_heap.py
gild/utils/widgets/__init__.py
gild/utils/widgets/dict_tree_view.enaml
gild/utils/widgets/list_editor.enaml
gild/utils/widgets/qt_clipboard.py
gild/utils/widgets/qt_list_str_widget.py
gild/utils/widgets/qt_tree_menu.enaml
gild/utils/widgets/qt_tree_widget.py
gild/utils/widgets/tree_nodes.py
gild-0.1.0.dist-info/LICENSE
gild-0.1.0.dist-info/METADATA
gild-0.1.0.dist-info/WHEEL
gild-0.1.0.dist-info/top_level.txt
gild-0.1.0.dist-info/RECORD
