Metadata-Version: 2.1
Name: gild
Version: 0.1.0
Summary: App building plugins for Enaml based plugin applications
Author-email: "Matthieu C. Dartiailh" <m.dartiailh@gmail.com>
License: Copyright (c) 2020-2022, Gild authors
Project-URL: homepage, https://github.com/MatthieuDartiailh/gild
Project-URL: documentation, https://gild.readthedocs.io/en/latest/
Project-URL: repository, https://github.com/MatthieuDartiailh/gild
Project-URL: changelog, https://github.com/MatthieuDartiailh/gild/blob/main/doc/changelog.rst
Classifier: Development Status :: 3 - Alpha
Classifier: License :: OSI Approved :: BSD License
Classifier: Natural Language :: English
Classifier: Operating System :: OS Independent
Classifier: Programming Language :: Python
Classifier: Programming Language :: Python :: 3.9
Classifier: Programming Language :: Python :: 3.10
Classifier: Topic :: Software Development :: Libraries :: Python Modules
Requires-Python: >=3.9
License-File: LICENSE
Requires-Dist: enaml (>=0.15.2)
Requires-Dist: qtawesome
Requires-Dist: watchdog
Requires-Dist: rtoml
Provides-Extra: qt5-pyqt
Requires-Dist: enaml[qt5-pyqt] ; extra == 'qt5-pyqt'
Provides-Extra: qt5-pyside
Requires-Dist: enaml[qt5-pyside] ; extra == 'qt5-pyside'
Provides-Extra: qt6-pyqt
Requires-Dist: enaml[qt6-pyqt] ; extra == 'qt6-pyqt'
Provides-Extra: qt6-pyside
Requires-Dist: enaml[qt6-pyside] ; extra == 'qt6-pyside'
